pysds011/__init__.py
pysds011/__main__.py
pysds011/cli.py
pysds011/driver.py
pysds011-0.0.4.dist-info/AUTHORS.rst
pysds011-0.0.4.dist-info/LICENSE
pysds011-0.0.4.dist-info/METADATA
pysds011-0.0.4.dist-info/WHEEL
pysds011-0.0.4.dist-info/entry_points.txt
pysds011-0.0.4.dist-info/top_level.txt
pysds011-0.0.4.dist-info/RECORD
