Metadata-Version: 2.1
Name: pysds011
Version: 0.0.4
Summary: Python driver and command line application to interact with SDS011 PM sensor from Nova.
Home-page: https://github.com/michelepagot/pysds011
Author: Michele Pagot
Author-email: michele.pagot.dev@outlook.com
License: MIT
Project-URL: Documentation, https://pysds011.readthedocs.io/
Project-URL: Changelog, https://pysds011.readthedocs.io/en/latest/changelog.html
Project-URL: Issue Tracker, https://github.com/michelepagot/pysds011/issues
Keywords: sds011,dust,sensor
Platform: UNKNOWN
Classifier: Development Status :: 5 - Production/Stable
Classifier: Intended Audience :: Developers
Classifier: License :: OSI Approved :: MIT License
Classifier: Operating System :: Unix
Classifier: Operating System :: POSIX
Classifier: Operating System :: Microsoft :: Windows
Classifier: Programming Language :: Python
Classifier: Programming Language :: Python :: 2.7
Classifier: Programming Language :: Python :: 3
Classifier: Programming Language :: Python :: 3.5
Classifier: Programming Language :: Python :: 3.6
Classifier: Programming Language :: Python :: 3.7
Classifier: Programming Language :: Python :: 3.8
Classifier: Programming Language :: Python :: 3.9
Classifier: Programming Language :: Python :: Implementation :: CPython
Classifier: Programming Language :: Python :: Implementation :: PyPy
Classifier: Topic :: Utilities
Requires-Python: >=2.7, !=3.0.*, !=3.1.*, !=3.2.*, !=3.3.*, !=3.4.*
Requires-Dist: click
Requires-Dist: click-log
Requires-Dist: pyserial
